setup.py
magneto/__init__.py
magneto/base.py
magneto/imagneto.py
magneto/logger.py
magneto/main.py
magneto.egg-info/PKG-INFO
magneto.egg-info/SOURCES.txt
magneto.egg-info/dependency_links.txt
magneto.egg-info/entry_points.txt
magneto.egg-info/requires.txt
magneto.egg-info/top_level.txt
magneto/utils/__init__.py
magneto/utils/adb.py
magneto/utils/assertion.py