Metadata-Version: 1.1
Name: magneto
Version: 0.38
Summary: Magneto - Test Automation for Android
Home-page: http://github.com/EverythingMe/magneto
Author: EverythingMe
Author-email: automation@everything.me
License: UNKNOWN
Platform: UNKNOWN
Classifier: Development Status :: 3 - Alpha
Classifier: Environment :: Console
Classifier: Intended Audience :: Developers
Classifier: Operating System :: OS Independent
Classifier: Programming Language :: Python :: 2.7
Classifier: Topic :: Software Development :: Quality Assurance
Classifier: Topic :: Software Development :: Testing
